LICENSE
MANIFEST.in
README.md
VERSION
check_sage_testsuite.py
pyproject.toml
setup.py
passagemath_coin_or_cbc.egg-info/PKG-INFO
passagemath_coin_or_cbc.egg-info/SOURCES.txt
passagemath_coin_or_cbc.egg-info/dependency_links.txt
passagemath_coin_or_cbc.egg-info/requires.txt
passagemath_coin_or_cbc.egg-info/top_level.txt
sage_numerical_backends_coin/__init__.py
sage_numerical_backends_coin/coin_backend.pxd
sage_numerical_backends_coin/coin_backend.pyx